{"id":1004070,"name":"Son Goku Super Saiyan divin SS","cost":18,"rarity":"SSR","hp":7608,"atk":6346,"def":3299,"type":"TEQ","class":"SUPER","isAwakened":false,"maxLevel":80,"skillMaxLevel":10,"collection":"OTHER","resource":1004070,"year":0,"date":"2016-03-24T07:10:00.000Z","transformationFromId":null,"transformationId":null,"ezaId":null,"characterId":86,"leaderSkillId":100407,"passiveSkillId":394,"activeSkillId":null,"potentialId":null,"activeSkill":null,"awakened":[1008621],"categories":[17,30,84,39,8,76,79,40,29,65,80,83],"eza":null,"leaderSkill":{"id":100407,"name":"Broyeur du mal","description":"Alliés TEC ATT +30 % à chaque ki TEC \nobtenue"},"links":[29,47,68,70,71,97],"passiveSkill":{"id":394,"name":"Cri de combat ardent","description":"Change sphère de ki Arc-en-ciel en sphère \nde ki TEC"},"superAttacks":[{"id":233,"name":"Kamehameha divin","description":"Inflige des dégâts colossaux","type":"OTHER","ki":12,"increaseRate":150,"isEza":false}],"unawakened":[]}