{"id":1005741,"name":"Vegeta Super Saiyan 3","cost":42,"rarity":"UR","hp":7702,"atk":8158,"def":4362,"type":"TEQ","class":"SUPER","isAwakened":true,"maxLevel":120,"skillMaxLevel":10,"collection":"OTHER","resource":1005740,"year":1,"date":"2016-09-20T04:30:00.000Z","transformationFromId":null,"transformationId":null,"ezaId":18,"characterId":210,"leaderSkillId":100574,"passiveSkillId":544,"activeSkillId":null,"potentialId":21,"activeSkill":null,"awakened":[],"categories":[17,31,12,84,37,68,61],"eza":{"id":18,"hp":1,"atk":1,"def":1,"date":"2009-12-31T23:00:00.000Z","leaderSkillId":1005741,"passiveSkillId":1345,"leaderSkill":{"id":1005741,"name":"Pouvoir de décimer","description":"Ki +3, PV, ATT et DÉF +40 % pour tous les types"},"passiveSkill":{"id":1345,"name":"Position fatale","description":"ATT +90 % au début du tour ; \nsi ki à 10 ou plus, ki +2, DÉF +120 %"},"superAttacks":[{"id":1526,"name":"Final Flash (suprême)","description":"Inflige des dégâts colossaux \net diminue l'ATT","type":"OTHER","ki":12,"increaseRate":150,"isEza":false}]},"leaderSkill":{"id":100574,"name":"Pouvoir de décimer","description":"Ki +3 sur tous les types"},"links":[9,22,26,29,40,109,116],"passiveSkill":{"id":544,"name":"Position fatale","description":"ATT +70 % au début du tour"},"superAttacks":[{"id":254,"name":"Final Flash","description":"Inflige des dégâts colossaux","type":"OTHER","ki":12,"increaseRate":150,"isEza":false}],"unawakened":[1003240]}