{"id":1005391,"name":"Son Gohan Super Saiyan (enfant)","cost":36,"rarity":"UR","hp":8753,"atk":7790,"def":3636,"type":"INT","class":"SUPER","isAwakened":true,"maxLevel":120,"skillMaxLevel":10,"collection":"OTHER","resource":1005390,"year":1,"date":"2016-07-26T04:30:00.000Z","transformationFromId":null,"transformationId":null,"ezaId":58,"characterId":57,"leaderSkillId":100539,"passiveSkillId":495,"activeSkillId":null,"potentialId":122,"activeSkill":null,"awakened":[],"categories":[38,5,30,33,36,39,54,76,40,81,74],"eza":{"id":58,"hp":1,"atk":1,"def":1,"date":"2009-12-31T23:00:00.000Z","leaderSkillId":1005391,"passiveSkillId":1927,"leaderSkill":{"id":1005391,"name":"Envol de la nouvelle génération","description":"Ki +3, PV, ATT et DÉF +40 % \npour tous les types"},"passiveSkill":{"id":1927,"name":"Attentes paternelles","description":"Ki +4, ATT et DÉF +70 % ; \ns'il y a un perso dont le nom comprend \"Son Goku\" \n(hors enfant, Ginyu, Jr, etc.) parmi les alliés \nattaquants du tour, ATT +70 % en plus"},"superAttacks":[{"id":2092,"name":"Super Kamehameha (suprême)","description":"Augmente fortement la DÉF \npendant 1 tour et inflige \ndes dégâts colossaux à l'ennemi","type":"OTHER","ki":12,"increaseRate":150,"isEza":false}]},"leaderSkill":{"id":100539,"name":"Envol de la nouv. génération","description":"ATT et PV +25 % sur les types AGI, INT \net END"},"links":[9,22,29,47,56,118],"passiveSkill":{"id":495,"name":"Attentes paternelles","description":"ATT +2500 et ki +4 si PV au-dessus de 50 %"},"superAttacks":[{"id":124,"name":"Super Kamehameha","description":"Inflige des dégâts colossaux.","type":"OTHER","ki":12,"increaseRate":150,"isEza":false}],"unawakened":[1001390]}