{"id":1007420,"name":"Super Paikuhan","cost":19,"rarity":"SSR","hp":7147,"atk":6611,"def":3575,"type":"STR","class":"SUPER","isAwakened":false,"maxLevel":80,"skillMaxLevel":10,"collection":"OTHER","resource":1007420,"year":4,"date":"2019-08-13T04:30:00.000Z","transformationFromId":null,"transformationId":null,"ezaId":null,"characterId":291,"leaderSkillId":100742,"passiveSkillId":674,"activeSkillId":null,"potentialId":null,"activeSkill":null,"awakened":[1016751],"categories":[37,71,58,61,42],"eza":null,"leaderSkill":{"id":100742,"name":"Le secret de l'entraînement","description":"PV et ATT +20 % sur tous les types"},"links":[8,16,17,30,52,60],"passiveSkill":{"id":674,"name":"Chance incontournable","description":"ATT +10000 en face d'un seul ennemi"},"superAttacks":[{"id":450,"name":"Éclair foudroyant","description":"Inflige des dégâts colossaux \net réduit fortement l'ATT.","type":"OTHER","ki":12,"increaseRate":150,"isEza":false}],"unawakened":[]}