{"id":1007391,"name":"Golden Freezer","cost":48,"rarity":"UR","hp":9350,"atk":8980,"def":4475,"type":"TEQ","class":"EXTREME","isAwakened":true,"maxLevel":120,"skillMaxLevel":10,"collection":"DFE","resource":1007390,"year":1,"date":"2017-01-25T05:30:00.000Z","transformationFromId":null,"transformationId":null,"ezaId":34,"characterId":88,"leaderSkillId":100739,"passiveSkillId":665,"activeSkillId":null,"potentialId":21,"activeSkill":null,"awakened":[],"categories":[24,23,20,76,78,16,68,7,48,43,41,50,69,83],"eza":{"id":34,"hp":1,"atk":1,"def":1,"date":"2009-12-31T23:00:00.000Z","leaderSkillId":1007391,"passiveSkillId":1492,"leaderSkill":{"id":1007391,"name":"Le feu de la vengeance","description":"Ki +3, PV, ATT et DÉF +120 % pour le type TEC"},"passiveSkill":{"id":1492,"name":"L'heure de la contre-attaque","description":"ATT +80 % ; \nsi PV à 50 % ou plus, dégâts encaissés réduits de 80 % ; \nsi PV à 49 % ou moins, dégâts encaissés réduits de 50 % \net ATT +50 % en plus"},"superAttacks":[{"id":1732,"name":"Brise-terre (suprême)","description":"Inflige des dégâts immenses \net diminue énormément la DÉF","type":"OTHER","ki":12,"increaseRate":180,"isEza":false}]},"leaderSkill":{"id":100739,"name":"Le feu de la vengeance","description":"PV, ATT et DÉF +100 % sur le type TEC"},"links":[59,60,65,68,71,85,109],"passiveSkill":{"id":665,"name":"L'heure de la contre-attaque","description":"Dégâts subis réduits de 70 % & ATT +70 % \nsi PV à 50 % ou plus"},"superAttacks":[{"id":440,"name":"Brise-terre","description":"Inflige des dégâts immenses \net diminue fortement la DÉF","type":"OTHER","ki":12,"increaseRate":180,"isEza":false}],"unawakened":[1008730]}