{"id":1008531,"name":"Son Gohan Super Saiyan (futur)","cost":36,"rarity":"UR","hp":9220,"atk":8236,"def":4131,"type":"TEQ","class":"SUPER","isAwakened":true,"maxLevel":120,"skillMaxLevel":10,"collection":"OTHER","resource":1008530,"year":1,"date":"2017-01-11T05:30:00.000Z","transformationFromId":null,"transformationId":null,"ezaId":null,"characterId":232,"leaderSkillId":100853,"passiveSkillId":659,"activeSkillId":null,"potentialId":21,"activeSkill":null,"awakened":[],"categories":[38,19,5,30,36,39,40,63,55],"eza":null,"leaderSkill":{"id":100853,"name":"Le protecteur de l'espoir","description":"ATT +70 % sur le type TEC"},"links":[9,29,30,47,66,97,118],"passiveSkill":{"id":659,"name":"Volonté fumante","description":"ATT et DÉF +70 % si PV à 80 % ou moins"},"superAttacks":[{"id":435,"name":"Kamehameha","description":"Augmente fortement l'ATT \net inflige d'énormes dégâts.","type":"OTHER","ki":12,"increaseRate":70,"isEza":false}],"unawakened":[2000230]}