{"id":1009661,"name":"Majin Vegeta","cost":50,"rarity":"UR","hp":10206,"atk":9153,"def":4769,"type":"AGL","class":"EXTREME","isAwakened":true,"maxLevel":120,"skillMaxLevel":10,"collection":"OTHER","resource":1009660,"year":1,"date":"2017-06-12T04:30:00.000Z","transformationFromId":null,"transformationId":null,"ezaId":null,"characterId":115,"leaderSkillId":100966,"passiveSkillId":842,"activeSkillId":null,"potentialId":20,"activeSkill":null,"awakened":[1010161],"categories":[9,17,31,45,84,64,37,68,7],"eza":null,"leaderSkill":{"id":100966,"name":"Le combat final","description":"Ki +3, PV, ATT et DÉF +70 % sur le type \nAGI"},"links":[22,29,40,63,89,118],"passiveSkill":{"id":842,"name":"Combat à mort","description":"ATT +100 % lors d'une attaque spéciale"},"superAttacks":[{"id":642,"name":"Impact final","description":"Inflige des dégâts colossaux, \npeut rarement étourdir l'ennemi","type":"OTHER","ki":12,"increaseRate":150,"isEza":false}],"unawakened":[1010150]}