{"id":1009641,"name":"Boo (petit)","cost":58,"rarity":"UR","hp":11875,"atk":10800,"def":4688,"type":"INT","class":"EXTREME","isAwakened":true,"maxLevel":120,"skillMaxLevel":10,"collection":"DFE","resource":1009640,"year":2,"date":"2017-09-25T04:30:00.000Z","transformationFromId":null,"transformationId":null,"ezaId":103,"characterId":150,"leaderSkillId":100964,"passiveSkillId":863,"activeSkillId":null,"potentialId":22,"activeSkill":null,"awakened":[],"categories":[9,32,23,53,78,7,71,77,69,80,83,82],"eza":{"id":103,"hp":1,"atk":1,"def":1,"date":"2009-12-31T23:00:00.000Z","leaderSkillId":1009641,"passiveSkillId":2257,"leaderSkill":{"id":1009641,"name":"Le démon qui surpasse tout","description":"Ki +3, PV, ATT et DÉF +130 % pour le type E. INT ; \nki +3, PV, ATT et DÉF +90 % pour le type S. INT"},"passiveSkill":{"id":2257,"name":"Concentration extrême","description":"ATT +100 % ; si PV à 30 % ou plus, ATT et DÉF \n+70 % en plus ; si PV à 50 % ou plus, ki +1 pour \ntous les alliés de classe Extrême de catégorie \n\"Pouvoir de Majin\" ; si PV à 70 % ou plus, \nki +1 pour tous les alliés de classe Extrême"},"superAttacks":[{"id":2747,"name":"Super anéantissement de la Terre (suprême)","description":"Augmente l'ATT et la DÉF pendant 1 tour, \ninflige des dégâts immenses et récupère 12 % des PV","type":"OTHER","ki":12,"increaseRate":180,"isEza":false}]},"leaderSkill":{"id":100964,"name":"Le démon qui surpasse tout","description":"Ki +3, PV, ATT et DÉF +120 % sur le type \nE. INT ; Ki +1, PV, ATT et DÉF +50 % \nsur le type S. INT"},"links":[14,18,50,83,96,109,1004],"passiveSkill":{"id":863,"name":"Concentration extrême","description":"ATT +100 % et +70 % supplémentaires si \nPV à 30 % ou plus"},"superAttacks":[{"id":663,"name":"Super anéantissement de la Terre","description":"Inflige des dégâts immenses \net récup. 12 % des PV","type":"OTHER","ki":12,"increaseRate":180,"isEza":false}],"unawakened":[1009650]}