{"id":1010451,"name":"Bojack puissance max","cost":40,"rarity":"UR","hp":8145,"atk":7920,"def":4153,"type":"STR","class":"EXTREME","isAwakened":true,"maxLevel":120,"skillMaxLevel":10,"collection":"OTHER","resource":1010450,"year":2,"date":"2017-08-01T04:30:00.000Z","transformationFromId":null,"transformationId":null,"ezaId":null,"characterId":123,"leaderSkillId":101045,"passiveSkillId":855,"activeSkillId":null,"potentialId":13,"activeSkill":null,"awakened":[],"categories":[20,16,7,62,26,71,77,41,50],"eza":null,"leaderSkill":{"id":101045,"name":"Secousses énergétiques","description":"Ki +2, ATT et DÉF +50 % sur le type PUI"},"links":[32,50,86,87,88,118,1004],"passiveSkill":{"id":855,"name":"Coup bas","description":"ATT +90 % lors d'une attaque spéciale"},"superAttacks":[{"id":656,"name":"Buster galactique","description":"Inflige d'énormes dégâts \net diminue fortement la DÉF","type":"OTHER","ki":12,"increaseRate":120,"isEza":false}],"unawakened":[2000700,1002560]}