{"id":1013820,"name":"Vegeta Super Saiyan divin SS","cost":30,"rarity":"SSR","hp":7536,"atk":6843,"def":3866,"type":"AGL","class":"SUPER","isAwakened":false,"maxLevel":80,"skillMaxLevel":10,"collection":"DFE","resource":1013820,"year":3,"date":"2018-10-26T04:30:00.000Z","transformationFromId":null,"transformationId":null,"ezaId":null,"characterId":87,"leaderSkillId":101382,"passiveSkillId":1153,"activeSkillId":null,"potentialId":null,"activeSkill":null,"awakened":[1013831],"categories":[6,17,31,84,8,76,37,35,40,22,68],"eza":null,"leaderSkill":{"id":101382,"name":"Quête de la force","description":"Ki +2, PV et DÉF +140 %, ATT +100 % \npour la catégorie \"Saiyan pur\""},"links":[26,29,40,70,97,130],"passiveSkill":{"id":1153,"name":"Je gagnerai à ma façon","description":"ATT +100 % et DÉF +50 % ; \ngarantit deux attaques supplémentaires ; \nDÉF +6 % à chaque attaque portée (max. 60 %)"},"superAttacks":[{"id":1225,"name":"Gamma Burst Flash","description":"Inflige des dégâts immenses \net diminue fortement la DÉF","type":"OTHER","ki":12,"increaseRate":180,"isEza":false}],"unawakened":[]}