{"id":1016571,"name":"Son Goku (enfant)","cost":58,"rarity":"UR","hp":10630,"atk":10884,"def":5955,"type":"INT","class":"SUPER","isAwakened":true,"maxLevel":120,"skillMaxLevel":10,"collection":"DFE","resource":1016570,"year":3,"date":"2019-06-06T04:30:00.000Z","transformationFromId":null,"transformationId":null,"ezaId":null,"characterId":84,"leaderSkillId":101657,"passiveSkillId":1471,"activeSkillId":16,"potentialId":22,"activeSkill":{"id":16,"name":"Je vais te transpercer !","description":"Inflige des dégâts suprêmes","condition":"Peut être activée si PV à 59 % ou moins \n(1 fois seulement)"},"awakened":[],"categories":[34,17,30,33,39,20,60,67,54,79,40,65,11,25,57,48,80,83],"eza":null,"leaderSkill":{"id":101657,"name":"Tout ce que j'ai, dans mon poing","description":"Ki +3, PV, ATT et DÉF +170 % pour la \ncatégorie \"Arc enfant\" ou \nki +3, PV, ATT et DÉF +150 % pour la \ncatégorie \"Enfant\""},"links":[4,23,36,47,90,102,109],"passiveSkill":{"id":1471,"name":"Ultime pari !","description":"ATT et DÉF +77 %, plus les PV restants sont élevés, \nplus l'ATT augmente (max. 59 %), \nplus les PV restants sont bas, \nplus la DÉF augmente (max. 59 %) ; \nà chaque début de tour, ki +1, ATT et DÉF +10 % (max. 59 %) ; \nsi PV à 59 % ou moins, coup critique garanti (1 fois seulement)"},"superAttacks":[{"id":1667,"name":"Kamehameha ondulant","description":"Inflige des dégâts immenses, \nchance moyenne d'étourdir l'ennemi","type":"OTHER","ki":12,"increaseRate":180,"isEza":false}],"unawakened":[1016560]}