{"id":1016731,"name":"Baby Janemba","cost":40,"rarity":"UR","hp":8474,"atk":8134,"def":4717,"type":"AGL","class":"EXTREME","isAwakened":true,"maxLevel":120,"skillMaxLevel":10,"collection":"OTHER","resource":1016730,"year":4,"date":"2019-08-13T04:30:00.000Z","transformationFromId":null,"transformationId":null,"ezaId":197,"characterId":292,"leaderSkillId":101673,"passiveSkillId":1555,"activeSkillId":null,"potentialId":20,"activeSkill":null,"awakened":[],"categories":[32,23,64,41,61,42],"eza":{"id":197,"hp":1,"atk":1,"def":1,"date":"2009-12-31T23:00:00.000Z","leaderSkillId":1016731,"passiveSkillId":2639,"leaderSkill":{"id":1016731,"name":"Sublimation du mal et de la haine","description":"Ki +3, PV, ATT et DÉF +100 % pour le type AGI"},"passiveSkill":{"id":2639,"name":"Émanations de haine et de malice","description":"Au début du tour, récupère 12 % des PV, \nATT et DÉF +120 % ; grandes chances d'esquive \nde l'attaque ennemie (attaque spéciale incluse) et \nà chaque esquive, chances d'esquive +12 % en plus \nlors de ce tour ; lors d'une attaque spéciale, \nsi PV à 60 % ou plus, ATT et DÉF +120 % en plus"},"superAttacks":[{"id":3455,"name":"Porte de l'enfer (suprême)","description":"Augmente l'ATT pendant 1 tour, \ninflige des dégâts colossaux et \ndiminue énormément la DÉF","type":"OTHER","ki":12,"increaseRate":150,"isEza":false}]},"leaderSkill":{"id":101673,"name":"Sublimation du mal et de la haine","description":"Ki +3, PV, ATT et DÉF +80 % pour le type AGI"},"links":[28,32,60,86,115,118,120],"passiveSkill":{"id":1555,"name":"Émanations de haine et de malice","description":"Au début du tour, récupère 10 % des PV, ATT et DÉF +80 % ; \ngrandes chances d'esquiver l'attaque ennemie \n(attaque spéciale incluse)"},"superAttacks":[{"id":1817,"name":"Porte de l'enfer","description":"Inflige des dégâts colossaux et \ndiminue énormément la DÉF","type":"OTHER","ki":12,"increaseRate":150,"isEza":false}],"unawakened":[1007710]}