{"id":1017341,"name":"Cell (1re forme)","cost":38,"rarity":"UR","hp":9324,"atk":7231,"def":5807,"type":"TEQ","class":"EXTREME","isAwakened":true,"maxLevel":120,"skillMaxLevel":10,"collection":"F2P","resource":1017340,"year":4,"date":"2020-01-01T05:30:00.000Z","transformationFromId":null,"transformationId":null,"ezaId":null,"characterId":6,"leaderSkillId":101734,"passiveSkillId":1592,"activeSkillId":null,"potentialId":21,"activeSkill":null,"awakened":[1017351],"categories":[38,21,32,23,59,78,26,43,82],"eza":null,"leaderSkill":{"id":101734,"name":"Un monstre avec l'aura de Goku","description":"Ki +2, PV, ATT et DÉF +70 % \npour la catégorie \"Vie artificielle\""},"links":[12,19,47,50,60,118],"passiveSkill":{"id":1592,"name":"Cellules de maîtres","description":"ATT et DÉF +15000 ; \nki +1 à chaque attaque spéciale (max. +4)"},"superAttacks":[{"id":1854,"name":"Kamehameha","description":"Inflige des dégâts colossaux, \nrécupération de 10 % des PV","type":"OTHER","ki":12,"increaseRate":150,"isEza":false}],"unawakened":[1017330]}