{"id":1021070,"name":"Freezer (1re forme)","cost":13,"rarity":"SSR","hp":6523,"atk":6168,"def":3847,"type":"TEQ","class":"EXTREME","isAwakened":false,"maxLevel":80,"skillMaxLevel":10,"collection":"F2P","resource":1021070,"year":5,"date":"2021-01-04T05:30:00.000Z","transformationFromId":null,"transformationId":null,"ezaId":null,"characterId":5,"leaderSkillId":102107,"passiveSkillId":2255,"activeSkillId":null,"potentialId":null,"activeSkill":null,"awakened":[1021081],"categories":[41],"eza":null,"leaderSkill":{"id":102107,"name":"Premier entraînement","description":"Ki +1, PV, ATT et DÉF +25 % pour le type TEC"},"links":[8,26,32,39,72,86],"passiveSkill":{"id":2255,"name":"Entraînement strict","description":"Si PV à 50 % ou plus, ATT et DÉF +90 % ; si PV à \n49 % ou moins, dégâts encaissés réduits de 30 %"},"superAttacks":[{"id":2733,"name":"Rayon mortel","description":"Inflige des dégâts colossaux","type":"OTHER","ki":12,"increaseRate":150,"isEza":false}],"unawakened":[]}