{"id":1021340,"name":"Son Gohan ultime","cost":21,"rarity":"SSR","hp":7066,"atk":6405,"def":3508,"type":"TEQ","class":"SUPER","isAwakened":false,"maxLevel":80,"skillMaxLevel":10,"collection":"OTHER","resource":1021340,"year":6,"date":"2021-07-09T01:00:00.000Z","transformationFromId":null,"transformationId":null,"ezaId":null,"characterId":149,"leaderSkillId":102134,"passiveSkillId":2348,"activeSkillId":null,"potentialId":null,"activeSkill":null,"awakened":[1021351],"categories":[6,39,40,22,58],"eza":null,"leaderSkill":{"id":102134,"name":"Leader de l'équipe Univers 7","description":"Ki +2, PV, ATT et DÉF +100 % \npour la catégorie \"Lien maître et disciple\""},"links":[8,37,39,47,53,130],"passiveSkill":{"id":2348,"name":"Détermination du leader","description":"À chaque début de tour, ATT et DÉF +15 % (max. \n60 %) ; lors d'une attaque spéciale, ATT et DÉF \n+80 % en plus et chance moyenne d'étourdir l'ennemi \nattaqué ; s'il y a parmi les alliés attaquants du tour un \nautre perso de catégorie \"Représentants de l'Univers 7\", \nATT et DÉF +20 % pour tous les alliés de catégorie \n\"Représentants de l'Univers 7\""},"superAttacks":[{"id":2869,"name":"Super Kamehameha","description":"Augmente l'ATT pendant 1 tour \net inflige des dégâts colossaux","type":"OTHER","ki":12,"increaseRate":150,"isEza":false}],"unawakened":[]}