{"id":1022941,"name":"Krillin & Son Gohan (petit)","cost":77,"rarity":"LR","hp":20088,"atk":14595,"def":9338,"type":"AGL","class":"SUPER","isAwakened":true,"maxLevel":150,"skillMaxLevel":20,"collection":"LEG","resource":1022940,"year":6,"date":"2021-09-16T04:00:00.000Z","transformationFromId":null,"transformationId":null,"ezaId":null,"characterId":634,"leaderSkillId":102294,"passiveSkillId":2576,"activeSkillId":109,"potentialId":20,"activeSkill":{"id":109,"name":"Déploie ta puissance !!","description":"Ki +24 pendant 1 tour","condition":"Peut être activée à partir du 3e \ntour après le début du combat \n(1 fois seulement)"},"awakened":[],"categories":[14,39,54,28,25],"eza":null,"leaderSkill":{"id":102294,"name":"Combat au pied du mur ","description":"Ki +4, PV, ATT et DÉF +130 % pour la catégorie \n\"Croissance rapide\" ou ki +4, PV, ATT et DÉF +100 % \npour le type AGI"},"links":[37,39,42,47,60,109,125],"passiveSkill":{"id":2576,"name":"Échange d'idées","description":"ATT et DÉF +130 % ; chance moyenne \nd'esquiver l'attaque ennemie (attaque spéciale incluse) ; \nki +1 en plus à chaque sph. de ki obtenue ; \nATT +50 % en plus lors d'une attaque spéciale ; \nsi ki à 24, attaque supplémentaire garantie et grandes \nchances d'attaque spéciale ; si les conditions sont \nremplies, revêt une tenue de combat"},"superAttacks":[{"id":3340,"name":"Combo ultra rapide","description":"Augmente l'ATT et la DÉF pendant 1 tour \net inflige des dégâts gigantesques","type":"OTHER","ki":12,"increaseRate":200,"isEza":false},{"id":3341,"name":"Kamehameha & Masenko","description":"Augmente fortement l'ATT et la DÉF pendant 1 tour \net inflige des dégâts titanesques","type":"OTHER","ki":18,"increaseRate":250,"isEza":false}],"unawakened":[1022920,1022931]}